{
  "Categorias": [
    {
      "Titulo": "Plataformas",
      "Subcategorias": [
        {
          "Titulo": "Disney+",
          "Imagem": "https://www.logo.wine/a/logo/Disney%2B/Disney%2B-White-Dark-Background-Logo.wine.svg",
          "Id": 1
        },
        {
          "Titulo": "HBO Max",
          "Imagem": "https://www.logo.wine/a/logo/HBO%2BMax/HBO%2BMax-Logo.wine.svg",
          "Id": 2
        },
        {
          "Titulo": "Prime Video",
          "Imagem": "https://www.logo.wine/a/logo/Prime%2BVideo/Prime%2BVideo-Logo.wine.svg",
          "Id": 3
        },
        {
          "Titulo": "Crunchyroll",
          "Imagem": "https://www.logo.wine/a/logo/Crunchyroll/Crunchyroll-Logo.wine.svg",
          "Id": 4
        },
        {
          "Titulo": "Netflix",
          "Imagem": "https://www.logo.wine/a/logo/Netflix/Netflix-Logo.wine.svg",
          "Id": 5
        },
        {
          "Titulo": "Discovery+",
          "Imagem": "https://www.logo.wine/a/logo/Discovery%2B/Discovery%2B-Logo.wine.svg",
          "Id": 6
        }
      ]
    },
    {
      "Titulo": "Filmes",
      "Subcategorias": [
        {
          "Titulo": "Eternos",
          "Imagem": "https://www.logo.wine/a/logo/Eternos/Eternos-Logo.wine.svg",
          "Id": 7
        },
        {
          "Titulo": "GhostBusters",
          "Imagem": "https://www.logo.wine/a/logo/GhostBusters/GhostBusters-Logo.wine.svg",
          "Id": 8
        },
        {
          "Titulo": "Cruella",
          "Imagem": "https://www.logo.wine/a/logo/Cruella/Cruella-Logo.wine.svg",
          "Id": 9
        },
        {
          "Titulo": "Shang Chi",
          "Imagem": "https://www.logo.wine/a/logo/Shang%20Chi/Shang%20Chi-Logo.wine.svg",
          "Id": 10
        },
        {
          "Titulo": "Kiss",
          "Imagem": "https://www.logo.wine/a/logo/Kiss/Kiss-Logo.wine.svg",
          "Id": 11
        },
        {
          "Titulo": "The Avengers",
          "Imagem": "https://www.logo.wine/a/logo/The%20Avengers/The%20Avengers-Logo.wine.svg",
          "Id": 12
        },
        {
          "Titulo": "A Maldição da casa do Lago",
          "Imagem": "https://www.logo.wine/a/logo/A%20Maldi%C3%A7%C3%A3o%20da%20casa%20do%20Lago/A%20Maldi%C3%A7%C3%A3o%20da%20casa%20do%20Lago-Logo.wine.svg",
          "Id": 13
        },
        {
          "Titulo": "Como se fosse a primeira vez",
          "Imagem": "https://www.logo.wine/a/logo/Como%20se%20fosse%20a%20primeira%20vez/Como%20se%20fosse%20a%20primeira%20vez-Logo.wine.svg",
          "Id": 14
        }
      ]
    },
    {
      "Titulo": "Séries",
      "Subcategorias": [
        {
          "Titulo": "Todo Mundo Odeia o Chris",
          "Imagem": "https://www.logo.wine/a/logo/Todo%20Mundo%20Odeia%20o%20Chris/Todo%20Mundo%20Odeia%20o%20Chris-Logo.wine.svg",
          "Id": 15
        },
        {
          "Titulo": "Mandalorian",
          "Imagem": "https://www.logo.wine/a/logo/Mandalorian/Mandalorian-Logo.wine.svg",
          "Id": 16
        },
        {
          "Titulo": "The 100",
          "Imagem": "https://www.logo.wine/a/logo/The%20100/The%20100-Logo.wine.svg",
          "Id": 17
        },
        {
          "Titulo": "Round 6",
          "Imagem": "https://www.logo.wine/a/logo/Round%206/Round%206-Logo.wine.svg",
          "Id": 18
        },
        {
          "Titulo": "Cosmos",
          "Imagem": "https://www.logo.wine/a/logo/Cosmos/Cosmos-Logo.wine.svg",
          "Id": 19
        },
        {
          "Titulo": "Invencível",
          "Imagem": "https://www.logo.wine/a/logo/Invenc%C3%ADvel/Invenc%C3%ADvel-Logo.wine.svg",
          "Id": 20
        },
        {
          "Titulo": "Rick and Morty",
          "Imagem": "https://www.logo.wine/a/logo/Rick%20and%20Morty/Rick%20and%20Morty-Logo.wine.svg",
          "Id": 21
        },
        {
          "Titulo": "Departamento de Conspiração",
          "Imagem": "https://www.logo.wine/a/logo/Departamento%20de%20Conspira%C3%A7%C3%A3o/Departamento%20de%20Conspira%C3%A7%C3%A3o-Logo.wine.svg",
          "Id": 22
        }
      ]
    },
    {
      "Titulo": "Animes",
      "Subcategorias": [
        {
          "Titulo": "Naruto",
          "Imagem": "https://www.logo.wine/a/logo/Naruto/Naruto-Logo.wine.svg",
          "Id": 23
        },
        {
          "Titulo": "One Piece",
          "Imagem": "https://www.logo.wine/a/logo/One%20Piece/One%20Piece-Logo.wine.svg",
          "Id": 24
        },
        {
          "Titulo": "Dragon Ball",
          "Imagem": "https://www.logo.wine/a/logo/Dragon%20Ball/Dragon%20Ball-Logo.wine.svg",
          "Id": 25
        },
        {
          "Titulo": "Hunter x Hunter",
          "Imagem": "https://www.logo.wine/a/logo/Hunter%20x%20Hunter/Hunter%20x%20Hunter-Logo.wine.svg",
          "Id": 26
        },
        {
          "Titulo": "One Punch Man",
          "Imagem": "https://www.logo.wine/a/logo/One%20Punch%20Man-Logo.wine.svg",
          "Id": 27
        },
        {
          "Titulo": "Jojo's Bizarre Adventure",
          "Imagem": "https://www.logo.wine/a/logo/Jojo%27s%20Bizarre%20Adventure/Jojo%27s%20Bizarre%20Adventure-Logo.wine.svg",
          "Id": 28
        },
        {
          "Titulo": "Akame ga Kill",
          "Imagem": "https://www.logo.wine/a/logo/Akame%20ga%20Kill/Akame%20ga%20Kill-Logo.wine.svg",
          "Id": 29
        },
        {
          "Titulo": "Platinum End",
          "Imagem": "https://www.logo.wine/a/logo/Platinum%20End/Platinum%20End-Logo.wine.svg",
          "Id": 30
        },
        {
          "Titulo": "My hero Academia",
          "Imagem": "https://www.logo.wine/a/logo/My%20hero%20Academia/My%20hero%20Academia-Logo.wine.svg",
          "Id": 31
        }
      ]
    }
  ]
}
